MANIFEST.in
setup.cfg
setup.py
mlfromscratch/__init__.py
mlfromscratch/demo.py
mlfromscratch.egg-info/PKG-INFO
mlfromscratch.egg-info/SOURCES.txt
mlfromscratch.egg-info/dependency_links.txt
mlfromscratch.egg-info/requires.txt
mlfromscratch.egg-info/top_level.txt
mlfromscratch/supervised_learning/__init__.py
mlfromscratch/supervised_learning/adaboost.py
mlfromscratch/supervised_learning/bayesian_regression.py
mlfromscratch/supervised_learning/decision_tree.py
mlfromscratch/supervised_learning/gradient_boosting.py
mlfromscratch/supervised_learning/k_nearest_neighbors.py
mlfromscratch/supervised_learning/linear_discriminant_analysis.py
mlfromscratch/supervised_learning/logistic_regression.py
mlfromscratch/supervised_learning/multi_class_lda.py
mlfromscratch/supervised_learning/multilayer_perceptron.py
mlfromscratch/supervised_learning/naive_bayes.py
mlfromscratch/supervised_learning/perceptron.py
mlfromscratch/supervised_learning/perceptron_opt.py
mlfromscratch/supervised_learning/random_forest.py
mlfromscratch/supervised_learning/regression.py
mlfromscratch/supervised_learning/support_vector_machine.py
mlfromscratch/supervised_learning/xgboost.py
mlfromscratch/unsupervised_learning/__init__.py
mlfromscratch/unsupervised_learning/apriori.py
mlfromscratch/unsupervised_learning/dbscan.py
mlfromscratch/unsupervised_learning/fp_growth.py
mlfromscratch/unsupervised_learning/gaussian_mixture_model.py
mlfromscratch/unsupervised_learning/k_means.py
mlfromscratch/unsupervised_learning/partitioning_around_medoids.py
mlfromscratch/unsupervised_learning/principal_component_analysis.py
mlfromscratch/utils/__init__.py
mlfromscratch/utils/activation_functions.py
mlfromscratch/utils/data_manipulation.py
mlfromscratch/utils/data_operation.py
mlfromscratch/utils/kernels.py
mlfromscratch/utils/loss_functions.py
mlfromscratch/utils/optimizers.py